LICENSE
README.md
build/lib.macosx-11.0-arm64-cpython-311/fast_gae/fast_gae.cpython-311-darwin.so
fast_gae/__init__.py
fast_gae/fast_gae.cpython-311-darwin.so
fast_gae/fast_gae.pyx
setup.py
fast_gae-0.0.4.dist-info/LICENSE
fast_gae-0.0.4.dist-info/METADATA
fast_gae-0.0.4.dist-info/WHEEL
fast_gae-0.0.4.dist-info/RECORD
